astrolabe/__init__.py
astrolabe/exceptions.py
astrolabe/interval.py
astrolabe-0.4.0.dist-info/DESCRIPTION.rst
astrolabe-0.4.0.dist-info/METADATA
astrolabe-0.4.0.dist-info/pydist.json
astrolabe-0.4.0.dist-info/RECORD
astrolabe-0.4.0.dist-info/top_level.txt
astrolabe-0.4.0.dist-info/WHEEL
tests/__init__.py
tests/test_interval.py
