Metadata-Version: 2.0
Name: astrolabe
Version: 0.4.0
Summary: Timer library for recording performance metrics.
Home-page: https://github.com/cyberdelia/astrolabe
Author: Timothée Peignier
Author-email: timothee.peignier@tryphon.org
License: Copyright (©) 2012-2014 Timothée Peignier <timothee.peignier@tryphon.org>
